{
	"chart":{
		"plotBackgroundColor":null,
		"plotBorderWidth":0,
		"plotShadow":false,
		"spacingTop":0,
		"spacingBottom":0,
		"marginTop":0,
		"marginBottom":0
	},
	"title":{
		"text":null,
		"align":"center",
		"verticalAlign":"middle",
		"y":60
	},
	"tooltip":{
		"pointFormat":"<b>{point.y} ({point.percentage:.1f}%)</b>"
	},
	"accessibility":{
		"point":{
			"valueSuffix":"%"
		}
	},
	"credits":{
		"enabled":false	
	},
	"plotOptions":{
		"pie":{
			"dataLabels":{
				"enabled":true,
				"distance":-50,
				"style":{
					"fontWeight":"bold",
					"color":"white"
				}
			},
			"startAngle":-90,
			"endAngle":90,
			"center":[
				"50%",
				"75%"
			],
			"size":"110%"
		}
	},
	"series":[]
}